MANIFEST.in
README.rst
setup.cfg
setup.py
jicparameters/__init__.py
jicparameters.egg-info/PKG-INFO
jicparameters.egg-info/SOURCES.txt
jicparameters.egg-info/dependency_links.txt
jicparameters.egg-info/requires.txt
jicparameters.egg-info/top_level.txt