Metadata-Version: 1.1
Name: jicparameters
Version: 0.1.0
Summary: Python package making it easier to work with lots of parameters
Home-page: https://github.com/JIC-CSB/jicparameters
Author: Tjelvar Olsson
Author-email: tjelvar.olsson@jic.ac.uk
License: MIT
Download-URL: https://github.com/JIC-CSB/jicparameters/tarball/0.1.0
Keywords: parameter,setting
Platform: UNKNOWN
Classifier: Development Status :: 3 - Alpha
Classifier: Intended Audience :: Developers
Classifier: Intended Audience :: Science/Research
Classifier: License :: OSI Approved :: MIT License
Classifier: Natural Language :: English
Classifier: Programming Language :: Python
Classifier: Programming Language :: Python :: 2
Classifier: Programming Language :: Python :: 2.7
Classifier: Programming Language :: Python :: 3
Classifier: Programming Language :: Python :: 3.3
Classifier: Programming Language :: Python :: 3.4
Classifier: Programming Language :: Python :: 3.5
Classifier: Topic :: Scientific/Engineering
